MANIFEST.in
README.rst
setup.py
docs/HISTORY.txt
docs/LICENSE.GPL
docs/LICENSE.txt
ftw/__init__.py
ftw.monitor.egg-info/PKG-INFO
ftw.monitor.egg-info/SOURCES.txt
ftw.monitor.egg-info/dependency_links.txt
ftw.monitor.egg-info/entry_points.txt
ftw.monitor.egg-info/namespace_packages.txt
ftw.monitor.egg-info/not-zip-safe
ftw.monitor.egg-info/requires.txt
ftw.monitor.egg-info/top_level.txt
ftw/monitor/__init__.py
ftw/monitor/autowarmup.py
ftw/monitor/command.py
ftw/monitor/configure.zcml
ftw/monitor/dump_metrics.py
ftw/monitor/health.py
ftw/monitor/interfaces.py
ftw/monitor/perf_metrics.py
ftw/monitor/server.py
ftw/monitor/testing.py
ftw/monitor/utils.py
ftw/monitor/warmup.py
ftw/monitor/browser/__init__.py
ftw/monitor/browser/configure.zcml
ftw/monitor/browser/warmup.py
ftw/monitor/tests/__init__.py
ftw/monitor/tests/test_dump_metrics.py
ftw/monitor/tests/test_monitor_server.py
ftw/monitor/tests/test_perf_metrics.py
ftw/monitor/tests/test_utils.py
ftw/monitor/tests/test_warmup.py